README.md
setup.py
asyncredisrpc/__init__.py
asyncredisrpc/client.py
asyncredisrpc/server.py
asyncredisrpc.egg-info/PKG-INFO
asyncredisrpc.egg-info/SOURCES.txt
asyncredisrpc.egg-info/dependency_links.txt
asyncredisrpc.egg-info/requires.txt
asyncredisrpc.egg-info/top_level.txt